mlopscfg/__init__.py
mlopscfg/backend.py
mlopscfg/cli.py
mlopscfg/environment.py
mlopscfg/parameters.py
mlopscfg/parameters_cache.py
mlopscfg/struct_log.py
mlopscfg-1.0.1.dist-info/METADATA
mlopscfg-1.0.1.dist-info/WHEEL
mlopscfg-1.0.1.dist-info/entry_points.txt
mlopscfg-1.0.1.dist-info/RECORD
