Metadata-Version: 2.1
Name: mlopscfg
Version: 1.0.1
Summary: Library that abstracts metadata management for MLOps.
Author: TMNL MLOps Team
Requires-Python: >=3.9,<4.0
Classifier: Programming Language :: Python :: 3
Classifier: Programming Language :: Python :: 3.9
Classifier: Programming Language :: Python :: 3.10
Classifier: Programming Language :: Python :: 3.11
Requires-Dist: PyYAML (>=6.0)
Requires-Dist: boto3 (>=1.26.133)
Requires-Dist: click (>=8.0)
Requires-Dist: pyDeprecate (>=0.3.2,<0.4.0)
